cellmaps_pipeline/__init__.py
cellmaps_pipeline/cellmaps_cywebserviceapp.py
cellmaps_pipeline/cellmaps_pipelinecmd.py
cellmaps_pipeline/exceptions.py
cellmaps_pipeline/runner.py
cellmaps_pipeline-1.3.0.data/scripts/cellmaps_cywebserviceapp.py
cellmaps_pipeline-1.3.0.data/scripts/cellmaps_pipelinecmd.py
cellmaps_pipeline-1.3.0.dist-info/licenses/AUTHORS.rst
cellmaps_pipeline-1.3.0.dist-info/licenses/LICENSE
cellmaps_pipeline-1.3.0.dist-info/METADATA
cellmaps_pipeline-1.3.0.dist-info/WHEEL
cellmaps_pipeline-1.3.0.dist-info/top_level.txt
cellmaps_pipeline-1.3.0.dist-info/RECORD
