Metadata-Version: 2.4
Name: cellmaps_pipeline
Version: 1.3.0
Summary: Runs full Cell Maps pipeline
Home-page: https://github.com/idekerlab/cellmaps_pipeline
Author: Cell Maps team
Author-email: tools@cm4ai.org
License: MIT license
Keywords: cellmaps_pipeline
Classifier: Development Status :: 2 - Pre-Alpha
Classifier: Intended Audience :: Developers
Classifier: License :: OSI Approved :: MIT License
Classifier: Natural Language :: English
Classifier: Programming Language :: Python :: 3.8
Classifier: Programming Language :: Python :: 3.9
Classifier: Programming Language :: Python :: 3.10
Classifier: Programming Language :: Python :: 3.11
License-File: LICENSE
License-File: AUTHORS.rst
Requires-Dist: scipy<1.13.0
Requires-Dist: cellmaps_utils==0.9.0
Requires-Dist: cellmaps_imagedownloader==0.3.0
Requires-Dist: cellmaps_ppidownloader==0.2.2
Requires-Dist: cellmaps_image_embedding==0.3.3
Requires-Dist: cellmaps_ppi_embedding==0.4.3
Requires-Dist: cellmaps_coembedding==1.3.1
Requires-Dist: cellmaps_generate_hierarchy==0.2.4
Requires-Dist: cellmaps_hierarchyeval==0.2.2
Requires-Dist: networkx<2.9,>=2.8
Requires-Dist: tqdm<5.0.0,>=4.66.0
Dynamic: author
Dynamic: author-email
Dynamic: classifier
Dynamic: description
Dynamic: description-content-type
Dynamic: home-page
Dynamic: keywords
Dynamic: license
Dynamic: license-file
Dynamic: requires-dist
Dynamic: summary
